Metadata-Version: 2.1
Name: odoo10-addon-product-supplierinfo-for-customer-invoice
Version: 10.0.1.0.1
Summary: Based on product_customer_code, this module loads in every account invoice the customer code defined in the product,
Home-page: http://www.agilebg.com
Author: Agile Business Group,Odoo Community Association (OCA)
Author-email: support@odoo-community.org
License: AGPL-3
Platform: UNKNOWN
Classifier: Programming Language :: Python
Classifier: Framework :: Odoo
Classifier: License :: OSI Approved :: GNU Affero General Public License v3
Requires-Python: ~=2.7
Requires-Dist: odoo10-addon-product-supplierinfo-for-customer
Requires-Dist: odoo (<10.1dev,>=10.0)
